pydefi_simulator/__init__.py
pydefi_simulator/logger.py
pydefi_simulator/py.typed
pydefi_simulator/api/__init__.py
pydefi_simulator/api/coingecko.py
pydefi_simulator/api/config/__init__.py
pydefi_simulator/api/config/api_keys.yaml.template
pydefi_simulator/api/config/get_key.py
pydefi_simulator/api/config/path.py
pydefi_simulator/api/graphql/__init__.py
pydefi_simulator/api/graphql/thegraph.py
pydefi_simulator/api/graphql/zxgraph.py
pydefi_simulator/configs/__init__.py
pydefi_simulator/configs/aave/__init__.py
pydefi_simulator/configs/aave/config.yaml
pydefi_simulator/configs/aave/config_reader.py
pydefi_simulator/configs/aave/position.py
pydefi_simulator/configs/aave/platforms/__init__.py
pydefi_simulator/configs/aave/platforms/aave_factory.py
pydefi_simulator/configs/aave/platforms/aave_v2_factory.py
pydefi_simulator/configs/aave/platforms/aave_v3_factory.py
pydefi_simulator/currency/__init__.py
pydefi_simulator/currency/currency.py
pydefi_simulator/currency/currency_factory.py
pydefi_simulator/defi/__init__.py
pydefi_simulator/defi/information.py
pydefi_simulator/defi/wallet.py
pydefi_simulator/defi/managers/__init__.py
pydefi_simulator/defi/managers/defi_manager.py
pydefi_simulator/defi/managers/loop_manager.py
pydefi_simulator/defi/metrics/__init__.py
pydefi_simulator/defi/metrics/borrowing_metrics.py
pydefi_simulator/defi/metrics/defi_metrics.py
pydefi_simulator/defi/metrics/lending_metrics.py
pydefi_simulator/defi/platform/__init__.py
pydefi_simulator/defi/platform/defi_platform.py
pydefi_simulator/defi/position/__init__.py
pydefi_simulator/defi/position/defi_position.py
pydefi_simulator/price/__init__.py
pydefi_simulator/price/converter.py
pydefi_simulator/utils/__init__.py
pydefi_simulator/utils/contants.py
pydefi_simulator/utils/random_address.py
pydefi_simulator/utils/singleton.py
pydefi_simulator/utils/yaml_reader.py
pydefi_simulator/wallet/__init__.py
pydefi_simulator/wallet/manager.py
pydefi_simulator/wallet/wallet.py
pydefi_simulator-0.1.0.dist-info/METADATA
pydefi_simulator-0.1.0.dist-info/WHEEL
pydefi_simulator-0.1.0.dist-info/licenses/LICENSE
pydefi_simulator-0.1.0.dist-info/RECORD
