Metadata-Version: 2.4
Name: pydefi-simulator
Version: 0.1.0
Summary: DeFi simulator for testing lending and borrowing strategies.
Author: Robin Nogues
Author-email: robin.nogues@google.com
License-File: LICENSE
Keywords: cryptocurrency,defi,simulator
Classifier: Development Status :: 3 - Alpha
Classifier: Intended Audience :: Developers
Classifier: License :: OSI Approved :: MIT License
Classifier: Programming Language :: Python
Classifier: Programming Language :: Python :: 3.11
Classifier: Programming Language :: Python :: 3.12
Classifier: Programming Language :: Python :: 3.13
Requires-Python: >=3.11
Requires-Dist: pyyaml>=6.0.2
Requires-Dist: requests>=2.32.3
